char_similar/__init__.py
char_similar/char_similarity_class_pool.py
char_similar/char_similarity_multi.py
char_similar/char_similarity_std.py
char_similar/const_dict.py
char_similar/version.py
char_similar/conf/__init__.py
char_similar/conf/path_config.py
char_similar/data/__init__.py
char_similar/data/char_component.dict
char_similar/data/char_fourangle.dict
char_similar/data/char_frequency.dict
char_similar/data/char_number.dict
char_similar/data/char_order.dict
char_similar/data/char_pinyin.dict
char_similar/data/char_stroke.dict
char_similar/data/char_struct.dict
tet/__init__.py
tet/tet_char_similar_multi.py
tet/tet_char_similar_pool.py
tet/tet_char_similar_std.py
tet/tet_collect_sim.py
tet/data/__init__.py
char_similar-0.0.2.dist-info/LICENSE
char_similar-0.0.2.dist-info/METADATA
char_similar-0.0.2.dist-info/WHEEL
char_similar-0.0.2.dist-info/top_level.txt
char_similar-0.0.2.dist-info/RECORD
