Metadata-Version: 2.1
Name: char-similar
Version: 0.0.2
Summary: char-similar: Tookit of Chinese Character Similarity, Especially the Shape of the Characters.
Home-page: https://github.com/yongzhuo/char-similar
Author: yongzhuo
Author-email: 1903865025@qq.com
License: MIT
Classifier: License :: OSI Approved :: MIT License
Classifier: Programming Language :: Python :: 3.5
Classifier: Programming Language :: Python :: 3.6
Classifier: Programming Language :: Python :: 3.7
Classifier: Programming Language :: Python :: 3.8
Classifier: Programming Language :: Python :: 3.9
Classifier: Programming Language :: Python :: 3.10
Classifier: Programming Language :: Python :: 3.11
Classifier: Programming Language :: Python :: Implementation :: CPython
Classifier: Programming Language :: Python :: Implementation :: PyPy
License-File: LICENSE
Requires-Dist: macropodus (==0.0.7)
Requires-Dist: tqdm (==4.31.1)
